LICENSE
splatlog/__init__.py
splatlog/json/__init__.py
splatlog/json/default_handlers.py
splatlog/json/json_encoder.py
splatlog/json/json_formatter.py
splatlog/json/json_typings.py
splatlog/levels.py
splatlog/lib/__init__.py
splatlog/lib/collections.py
splatlog/lib/colors.py
splatlog/lib/functions/__init__.py
splatlog/lib/functions/slot_cached_property.py
splatlog/lib/proxy.py
splatlog/lib/rich/__init__.py
splatlog/lib/rich/constants.py
splatlog/lib/rich/enrich.py
splatlog/lib/rich/enriched_type.py
splatlog/lib/rich/formatter/__init__.py
splatlog/lib/rich/formatter/rich_formatter.py
splatlog/lib/rich/formatter/rich_repr.py
splatlog/lib/rich/formatter/rich_text.py
splatlog/lib/rich/inline.py
splatlog/lib/rich/ntv_table.py
splatlog/lib/rich/typings.py
splatlog/lib/text.py
splatlog/lib/typeguard.py
splatlog/locking.py
splatlog/named_handlers.py
splatlog/names.py
splatlog/rich_handler.py
splatlog/setup.py
splatlog/splat_handler.py
splatlog/splat_logger.py
splatlog/typings.py
splatlog/verbosity/__init__.py
splatlog/verbosity/verbosity_level_resolver.py
splatlog/verbosity/verbosity_levels_filter.py
splatlog/verbosity/verbosity_state.py
splatlog-0.3.4.dist-info/LICENSE
splatlog-0.3.4.dist-info/METADATA
splatlog-0.3.4.dist-info/WHEEL
splatlog-0.3.4.dist-info/RECORD
