Metadata-Version: 2.1
Name: splatlog
Version: 0.3.4
Summary: Python logger that accepts ** values and prints 'em out.
Home-page: https://github.com/nrser/splatlog
License: BSD-3-Clause
Author: nrser
Author-email: neil@neilsouza.com
Requires-Python: >=3.10,<4.0
Classifier: License :: OSI Approved :: BSD License
Classifier: Programming Language :: Python :: 3
Classifier: Programming Language :: Python :: 3.10
Classifier: Programming Language :: Python :: 3.11
Requires-Dist: rich (>=9)
Requires-Dist: typeguard (==3.0.0b2)
Project-URL: Documentation, http://nrser.com/splatlog
Project-URL: Repository, https://github.com/nrser/splatlog
